concrete/__init__.py
concrete/lang/__init__.py
concrete/lang/dialects/_FHE_ops_gen.py
concrete/lang/dialects/_ods_common.py
concrete/lang/dialects/fhe.py
concrete/lang/dialects/__init__.py
concrete/lang/dialects/fhelinalg.py
concrete/lang/dialects/_FHELinalg_ops_gen.py
concrete/compiler/jit_lambda.py
concrete/compiler/jit_support.py
concrete/compiler/jit_compilation_result.py
concrete/compiler/lambda_argument.py
concrete/compiler/wrapper.py
concrete/compiler/evaluation_keys.py
concrete/compiler/public_arguments.py
concrete/compiler/__init__.py
concrete/compiler/client_parameters.py
concrete/compiler/compilation_options.py
concrete/compiler/compilation_feedback.py
concrete/compiler/library_compilation_result.py
concrete/compiler/public_result.py
concrete/compiler/key_set_cache.py
concrete/compiler/library_support.py
concrete/compiler/client_support.py
concrete/compiler/utils.py
concrete/compiler/key_set.py
concrete/compiler/library_lambda.py
mlir/ir.py
mlir/execution_engine.py
mlir/passmanager.py
mlir/runtime/np_to_memref.py
mlir/runtime/__init__.py
mlir/conversions/__init__.py
mlir/transforms/__init__.py
mlir/_mlir_libs/_mlirLinalgPasses.cpython-310-x86_64-linux-gnu.so
mlir/_mlir_libs/_mlirDialectsSparseTensor.cpython-310-x86_64-linux-gnu.so
mlir/_mlir_libs/_mlirAsyncPasses.cpython-310-x86_64-linux-gnu.so
mlir/_mlir_libs/_mlir.cpython-310-x86_64-linux-gnu.so
mlir/_mlir_libs/_mlirGPUPasses.cpython-310-x86_64-linux-gnu.so
mlir/_mlir_libs/_mlirAllPassesRegistration.cpython-310-x86_64-linux-gnu.so
mlir/_mlir_libs/_mlirTransforms.cpython-310-x86_64-linux-gnu.so
mlir/_mlir_libs/_mlirDialectsQuant.cpython-310-x86_64-linux-gnu.so
mlir/_mlir_libs/__init__.py
mlir/_mlir_libs/_concretelang.cpython-310-x86_64-linux-gnu.so
mlir/_mlir_libs/_mlirExecutionEngine.cpython-310-x86_64-linux-gnu.so
mlir/_mlir_libs/_mlirConversions.cpython-310-x86_64-linux-gnu.so
mlir/_mlir_libs/_mlirDialectsLinalg.cpython-310-x86_64-linux-gnu.so
concrete_compiler-0.23.4.dist-info/METADATA
concrete_compiler-0.23.4.dist-info/WHEEL
concrete_compiler-0.23.4.dist-info/top_level.txt
concrete_compiler-0.23.4.dist-info/RECORD
