Metadata-Version: 2.1
Name: concrete-compiler
Version: 0.23.4
Summary: Concrete Compiler
Home-page: https://github.com/zama-ai/concrete-compiler
Author: Zama Team
Author-email: hello@zama.ai
License: BSD-3
Keywords: homomorphic encryption compiler
Classifier: Programming Language :: C++
Classifier: Programming Language :: Python :: 3
Classifier: Topic :: Software Development :: Compilers
Classifier: Topic :: Security :: Cryptography
Requires-Dist: numpy
Requires-Dist: PyYAML
Requires-Dist: setuptools
